MG23117UNO/__init__.py
MG23117UNO/fraccion.py
MG23117UNO/metodos.py
mg23117uno-0.1.2.dist-info/licenses/License
mg23117uno-0.1.2.dist-info/METADATA
mg23117uno-0.1.2.dist-info/WHEEL
mg23117uno-0.1.2.dist-info/top_level.txt
mg23117uno-0.1.2.dist-info/RECORD
