Metadata-Version: 2.4
Name: MG23117UNO
Version: 0.1.2
Summary: Libreria de resolución de sistemas de ecuaciones con algunos métodos matematicos conocidos
Home-page: https://github.com/mg23117/MG23117UNO
Author: Kevin Martínez
Author-email: Kevin Martínez <mg23117@ues.edu.sv>
License: MIT
Project-URL: Homepage, https://github.com/mg23117/MG23117UNO
Project-URL: Documentation, https://github.com/mg23117/MG23117UNO#readme
Classifier: Programming Language :: Python :: 3
Classifier: License :: OSI Approved :: MIT License
Classifier: Operating System :: OS Independent
Requires-Python: >=3.10
License-File: License
Requires-Dist: numpy>=1.24
Dynamic: author
Dynamic: home-page
Dynamic: license-file
Dynamic: requires-python
